vibelogger/__init__.py
vibelogger/config.py
vibelogger/exceptions.py
vibelogger/formatters.py
vibelogger/handlers.py
vibelogger/logger.py
vibelogger-0.1.1.dist-info/licenses/LICENSE
vibelogger-0.1.1.dist-info/METADATA
vibelogger-0.1.1.dist-info/WHEEL
vibelogger-0.1.1.dist-info/top_level.txt
vibelogger-0.1.1.dist-info/RECORD
