Metadata-Version: 2.4
Name: vibelogger
Version: 0.1.1
Summary: AI-Native Logging for LLM Agent Development
Author-email: VibeCoding Team <info@vibecoding.com>
License: MIT
Project-URL: Homepage, https://github.com/fladdict/vibe-logger
Project-URL: Repository, https://github.com/fladdict/vibe-logger
Project-URL: Documentation, https://github.com/fladdict/vibe-logger#readme
Project-URL: Issues, https://github.com/fladdict/vibe-logger/issues
Keywords: logging,ai,llm,development,vibecoding
Classifier: Development Status :: 3 - Alpha
Classifier: Intended Audience :: Developers
Classifier: Programming Language :: Python :: 3
Classifier: Programming Language :: Python :: 3.8
Classifier: Programming Language :: Python :: 3.9
Classifier: Programming Language :: Python :: 3.10
Classifier: Programming Language :: Python :: 3.11
Classifier: Programming Language :: Python :: 3.12
Classifier: Topic :: Software Development :: Libraries :: Python Modules
Classifier: Topic :: System :: Logging
Requires-Python: >=3.8
License-File: LICENSE
Provides-Extra: dev
Requires-Dist: pytest>=7.0; extra == "dev"
Requires-Dist: pytest-cov>=4.0; extra == "dev"
Requires-Dist: black>=22.0; extra == "dev"
Requires-Dist: flake8>=5.0; extra == "dev"
Requires-Dist: mypy>=1.0; extra == "dev"
Dynamic: license-file
